a10_neutron_lbaas/__init__.py
a10_neutron_lbaas/a10_config.py
a10_neutron_lbaas/a10_context.py
a10_neutron_lbaas/a10_exceptions.py
a10_neutron_lbaas/a10_openstack_lb.py
a10_neutron_lbaas/constants.py
a10_neutron_lbaas/handler_base.py
a10_neutron_lbaas/monkey_patch.py
a10_neutron_lbaas/plumbing_hooks.py
a10_neutron_lbaas/version.py
a10_neutron_lbaas/acos/__init__.py
a10_neutron_lbaas/acos/openstack_mappings.py
a10_neutron_lbaas/client_proxies/__init__.py
a10_neutron_lbaas/db/__init__.py
a10_neutron_lbaas/db/api.py
a10_neutron_lbaas/db/model_base.py
a10_neutron_lbaas/db/migration/__init__.py
a10_neutron_lbaas/db/migration/alembic.ini
a10_neutron_lbaas/db/migration/alembic_migrations/__init__.py
a10_neutron_lbaas/db/migration/alembic_migrations/env.py
a10_neutron_lbaas/db/migration/alembic_migrations/versions/08dacae1fb67_v2ssl.py
a10_neutron_lbaas/db/migration/alembic_migrations/versions/152ed5d509bc_scaling_group_member_virtual_server_1f.py
a10_neutron_lbaas/db/migration/alembic_migrations/versions/2782f2bd94aa_a10_appliance_scaling_group_table.py
a10_neutron_lbaas/db/migration/alembic_migrations/versions/2a280aba7701_create_orchestration.py
a10_neutron_lbaas/db/migration/alembic_migrations/versions/357cd913dae6_scaling_group_tenant_binding_table.py
a10_neutron_lbaas/db/migration/alembic_migrations/versions/3a4bbcea6e1e_a10_tenant_bindings_created_at_nullable.py
a10_neutron_lbaas/db/migration/alembic_migrations/versions/3c7123f2aeba_scaling_group_bindings_table.py
a10_neutron_lbaas/db/migration/alembic_migrations/versions/3e6dafba6b22_a10_scaling_group_tenant_binding_.py
a10_neutron_lbaas/db/migration/alembic_migrations/versions/4ffd7ee0f175_added_status_column_to_bindings_table.py
a10_neutron_lbaas/db/migration/alembic_migrations/versions/53ef3417bbaa_a10_device_instance_api_version_width.py
a10_neutron_lbaas/db/migration/alembic_migrations/versions/556f41dfda67_scaling_group_member_virtual_server_.py
a10_neutron_lbaas-1.8.1.dist-info/LICENSE
a10_neutron_lbaas-1.8.1.dist-info/METADATA
a10_neutron_lbaas-1.8.1.dist-info/WHEEL
a10_neutron_lbaas-1.8.1.dist-info/top_level.txt
a10_neutron_lbaas-1.8.1.dist-info/RECORD
