Metadata-Version: 2.1
Name: a10-neutron-lbaas
Version: 1.8.1
Summary: A10 Networks Openstack LBaaS Driver Middleware
Home-page: https://github.com/a10networks/a10-neutron-lbaas
Author: A10 Networks
Author-email: openstack@a10networks.com
License: Apache
Keywords: a10 axapi acos adc slb load balancer openstack neutron lbaas
Platform: UNKNOWN
Classifier: License :: OSI Approved :: Apache Software License
Classifier: Operating System :: POSIX
Classifier: Programming Language :: Python
Classifier: Programming Language :: Python :: 2.6
Classifier: Programming Language :: Python :: 2.7
Classifier: Topic :: Internet
Requires-Dist: acos-client (>=1.4.6)
Requires-Dist: a10-openstack-lib (>=0.2.1)
